LICENSE
MANIFEST.in
README.md
requirements.txt
setup.cfg
setup.py
sgmarkets_api_xsf_cofbox/__init__.py
sgmarkets_api_xsf_cofbox/__meta__.py
sgmarkets_api_xsf_cofbox/_dashboard.py
sgmarkets_api_xsf_cofbox/_obj_from_dict.py
sgmarkets_api_xsf_cofbox/_plot.py
sgmarkets_api_xsf_cofbox/_util.py
sgmarkets_api_xsf_cofbox/endpoint.py
sgmarkets_api_xsf_cofbox/info.py
sgmarkets_api_xsf_cofbox/request_cofbox_analysis.py
sgmarkets_api_xsf_cofbox/request_cofbox_analysis_types.py
sgmarkets_api_xsf_cofbox/request_cofbox_instruments.py
sgmarkets_api_xsf_cofbox/request_cofbox_instruments_details.py
sgmarkets_api_xsf_cofbox/response_cofbox_analysis.py
sgmarkets_api_xsf_cofbox/response_cofbox_analysis_types.py
sgmarkets_api_xsf_cofbox/response_cofbox_instruments.py
sgmarkets_api_xsf_cofbox/response_cofbox_instruments_details.py
sgmarkets_api_xsf_cofbox.egg-info/PKG-INFO
sgmarkets_api_xsf_cofbox.egg-info/SOURCES.txt
sgmarkets_api_xsf_cofbox.egg-info/dependency_links.txt
sgmarkets_api_xsf_cofbox.egg-info/not-zip-safe
sgmarkets_api_xsf_cofbox.egg-info/requires.txt
sgmarkets_api_xsf_cofbox.egg-info/top_level.txt
sgmarkets_api_xsf_cofbox/img/jupyter-logo.png
sgmarkets_api_xsf_cofbox/img/sg-logo.png
sgmarkets_api_xsf_cofbox/markdown/info.md