Metadata-Version: 1.1
Name: sgmarkets-api-xsf-cofbox
Version: 0.1.0
Summary: sgmarket api xsf COFBOX helper
Home-page: https://gitlab.com/sgmarkets/sgmarkets-api-xsf-cofbox
Author: sgmarkets
Author-email: olivier.borderies@gmail.com
License: MIT
Download-URL: https://gitlab.com/sgmarkets/sgmarkets-api-xsf-cofbox/repository/archive.tar.gz?ref=0.1.0
Keywords: sgmarkets,api,xsf,cofbox
Platform: UNKNOWN
Classifier: Development Status :: 4 - Beta
Classifier: License :: OSI Approved :: MIT License
Classifier: Programming Language :: Python :: 3.5
Classifier: Programming Language :: Python :: 3.6
Classifier: Programming Language :: Python :: 3.6
